{
  "timestamp": "2026-04-23T02:45:38.723Z",
  "nextUpdate": "2026-04-23T03:15:38.723Z",
  "stocks": {
    "PTPS": {
      "ticker": "PTPS",
      "price": 188,
      "change": -3,
      "changePct": -1.5706806282722512,
      "volume": 497800,
      "high": 191,
      "low": 188,
      "prevClose": 191,
      "source": "yahoo",
      "timestamp": "2026-04-23T02:45:32.511Z",
      "name": "PT Pulau Subur Tbk",
      "sector": "CPO/Plantation",
      "position": {
        "lots": 2832,
        "avgPrice": 190.17,
        "currentPrice": 188,
        "pnlPerShare": -2.1699999999999875,
        "totalPnl": -614543.9999999964,
        "pnlPct": -1.1410842930009926,
        "marketValue": 53241600
      }
    },
    "PGEO": {
      "ticker": "PGEO",
      "price": 1055,
      "change": 25,
      "changePct": 2.4271844660194173,
      "volume": 5338100,
      "high": 1055,
      "low": 1025,
      "prevClose": 1030,
      "source": "yahoo",
      "timestamp": "2026-04-23T02:45:33.069Z",
      "name": "Pertamina Geothermal Energy",
      "sector": "Geothermal/Energy",
      "position": {
        "lots": 370,
        "avgPrice": 1036.34,
        "currentPrice": 1055,
        "pnlPerShare": 18.660000000000082,
        "totalPnl": 690420.000000003,
        "pnlPct": 1.8005673813613374,
        "marketValue": 39035000
      }
    },
    "ESSA": {
      "ticker": "ESSA",
      "price": 875,
      "change": 15,
      "changePct": 1.744186046511628,
      "volume": 20245500,
      "high": 880,
      "low": 860,
      "prevClose": 860,
      "source": "yahoo",
      "timestamp": "2026-04-23T02:45:33.615Z",
      "name": "Surya Esa Perkasa Tbk",
      "sector": "Ammonia/Chemical",
      "position": {
        "lots": 445,
        "avgPrice": 791.18,
        "currentPrice": 875,
        "pnlPerShare": 83.82000000000005,
        "totalPnl": 3729990.0000000023,
        "pnlPct": 10.594302181551614,
        "marketValue": 38937500
      }
    },
    "ITMG": {
      "ticker": "ITMG",
      "price": 26900,
      "change": 100,
      "changePct": 0.3731343283582089,
      "volume": 334700,
      "high": 27050,
      "low": 26625,
      "prevClose": 26800,
      "source": "yahoo",
      "timestamp": "2026-04-23T02:45:34.174Z",
      "name": "Indo Tambangraya Megah",
      "sector": "Coal",
      "position": {
        "lots": 1,
        "avgPrice": 28167,
        "currentPrice": 26900,
        "pnlPerShare": -1267,
        "totalPnl": -126700,
        "pnlPct": -4.498171619270778,
        "marketValue": 2690000
      }
    },
    "ADRO": {
      "ticker": "ADRO",
      "price": 2520,
      "change": 0,
      "changePct": 0,
      "volume": 7324300,
      "high": 2550,
      "low": 2520,
      "prevClose": 2520,
      "source": "yahoo",
      "timestamp": "2026-04-23T02:45:34.747Z",
      "name": "Adaro Energy Indonesia",
      "sector": "Coal/Aluminum"
    },
    "AALI": {
      "ticker": "AALI",
      "price": 8400,
      "change": 100,
      "changePct": 1.2048192771084338,
      "volume": 409000,
      "high": 8400,
      "low": 8300,
      "prevClose": 8300,
      "source": "yahoo",
      "timestamp": "2026-04-23T02:45:35.317Z",
      "name": "Astra Agro Lestari",
      "sector": "CPO"
    },
    "LSIP": {
      "ticker": "LSIP",
      "price": 1790,
      "change": 5,
      "changePct": 0.2801120448179272,
      "volume": 4973100,
      "high": 1810,
      "low": 1780,
      "prevClose": 1785,
      "source": "yahoo",
      "timestamp": "2026-04-23T02:45:35.890Z",
      "name": "Lippo Sumatera Plantation",
      "sector": "CPO"
    },
    "ANTM": {
      "ticker": "ANTM",
      "price": 4120,
      "change": 20,
      "changePct": 0.4878048780487805,
      "volume": 11231500,
      "high": 4160,
      "low": 4090,
      "prevClose": 4100,
      "source": "yahoo",
      "timestamp": "2026-04-23T02:45:36.456Z",
      "name": "Aneka Tambang Tbk",
      "sector": "Nickel/Gold"
    },
    "INCO": {
      "ticker": "INCO",
      "price": 6750,
      "change": -125,
      "changePct": -1.8181818181818181,
      "volume": 1540300,
      "high": 6950,
      "low": 6725,
      "prevClose": 6875,
      "source": "yahoo",
      "timestamp": "2026-04-23T02:45:37.021Z",
      "name": "Vale Indonesia",
      "sector": "Nickel"
    },
    "BBRI": {
      "ticker": "BBRI",
      "price": 3250,
      "change": 10,
      "changePct": 0.30864197530864196,
      "volume": 37103300,
      "high": 3270,
      "low": 3240,
      "prevClose": 3240,
      "source": "yahoo",
      "timestamp": "2026-04-23T02:45:37.583Z",
      "name": "Bank Rakyat Indonesia",
      "sector": "Banking"
    },
    "BBCA": {
      "ticker": "BBCA",
      "price": 6500,
      "change": 50,
      "changePct": 0.7751937984496124,
      "volume": 16128800,
      "high": 6500,
      "low": 6425,
      "prevClose": 6450,
      "source": "yahoo",
      "timestamp": "2026-04-23T02:45:38.159Z",
      "name": "Bank Central Asia",
      "sector": "Banking"
    },
    "TLKM": {
      "ticker": "TLKM",
      "price": 3000,
      "change": 0,
      "changePct": 0,
      "volume": 9124300,
      "high": 3020,
      "low": 2990,
      "prevClose": 3000,
      "source": "yahoo",
      "timestamp": "2026-04-23T02:45:38.723Z",
      "name": "Telkom Indonesia",
      "sector": "Telecom"
    }
  },
  "portfolio": {
    "totalInvested": 130224934,
    "totalMarketValue": 133904100,
    "totalUnrealizedPnl": 3679166.000000009,
    "totalReturnPct": 2.825239289428251,
    "cash": 56000000,
    "totalEquity": 189904100
  },
  "meta": {
    "source": "mixed-yahoo-fallback",
    "isMarketOpen": true
  }
}